fcps_insys_api/__init__.py
fcps_insys_api/api/__init__.py
fcps_insys_api/api/courses/__init__.py
fcps_insys_api/api/courses/endpoints.py
fcps_insys_api/config.py
fcps_insys_api/main.py
fcps_insys_api/utils/__init__.py
fcps_insys_api/utils/main.py
fcps_insys_api-0.1.1.dist-info/METADATA
fcps_insys_api-0.1.1.dist-info/WHEEL
fcps_insys_api-0.1.1.dist-info/RECORD
