Metadata-Version: 2.1
Name: fcps_insys_api
Version: 0.1.1
Summary: API for FCPS Insys course catalog
Home-page: https://github.com/aarushtools/fcps-insys-api
License: MIT
Author: aarushtools
Requires-Python: >=3.12,<4.0
Classifier: License :: OSI Approved :: MIT License
Classifier: Programming Language :: Python :: 3
Classifier: Programming Language :: Python :: 3.12
Provides-Extra: server
Project-URL: Repository, https://github.com/aarushtools/fcps-insys-api
